djplacedata/__init__.py
djplacedata/apps.py
djplacedata/management/commands/__init__.py
djplacedata/management/commands/importplacedata.py
djplacedata/management/commands/importshapefiles.py
djplacedata/migrations/0001_initial.py
djplacedata/migrations/0002_alter_place_type.py
djplacedata/migrations/__init__.py
djplacedata/models.py
djplacedata/settings.py
djplacedata/utils.py
djplacedata/values.py
djplacedata/views.py
djplacedata-1.1.1.dist-info/WHEEL
djplacedata-1.1.1.dist-info/METADATA
djplacedata-1.1.1.dist-info/RECORD
