Metadata-Version: 2.1
Name: djplacedata
Version: 1.1.1
Summary: 
Author: Zach Perkitny
Requires-Python: >=3.6.2,<4.0.0
Classifier: Programming Language :: Python :: 3
Classifier: Programming Language :: Python :: 3.10
Classifier: Programming Language :: Python :: 3.7
Classifier: Programming Language :: Python :: 3.8
Classifier: Programming Language :: Python :: 3.9
Requires-Dist: Django (>=3.0)
Requires-Dist: census (>=0.8.18,<0.9.0)
Requires-Dist: census-shapefiles (==1.1.2)
Requires-Dist: sodapy (>=2.1.0,<3.0.0)
